timm_3d/__init__.py
timm_3d/version.py
timm_3d/data/__init__.py
timm_3d/data/auto_augment.py
timm_3d/data/config.py
timm_3d/data/constants.py
timm_3d/data/dataset.py
timm_3d/data/dataset_factory.py
timm_3d/data/dataset_info.py
timm_3d/data/distributed_sampler.py
timm_3d/data/imagenet_info.py
timm_3d/data/loader.py
timm_3d/data/mixup.py
timm_3d/data/random_erasing.py
timm_3d/data/real_labels.py
timm_3d/data/tf_preprocessing.py
timm_3d/data/transforms.py
timm_3d/data/transforms_factory.py
timm_3d/data/readers/__init__.py
timm_3d/data/readers/class_map.py
timm_3d/data/readers/img_extensions.py
timm_3d/data/readers/reader.py
timm_3d/data/readers/reader_factory.py
timm_3d/data/readers/reader_hfds.py
timm_3d/data/readers/reader_hfids.py
timm_3d/data/readers/reader_image_folder.py
timm_3d/data/readers/reader_image_in_tar.py
timm_3d/data/readers/reader_image_tar.py
timm_3d/data/readers/reader_tfds.py
timm_3d/data/readers/reader_wds.py
timm_3d/data/readers/shared_count.py
timm_3d/layers/__init__.py
timm_3d/layers/activations.py
timm_3d/layers/activations_jit.py
timm_3d/layers/activations_me.py
timm_3d/layers/adaptive_avgmax_pool.py
timm_3d/layers/attention_pool.py
timm_3d/layers/attention_pool2d.py
timm_3d/layers/blur_pool.py
timm_3d/layers/bottleneck_attn.py
timm_3d/layers/cbam.py
timm_3d/layers/classifier.py
timm_3d/layers/cond_conv2d.py
timm_3d/layers/config.py
timm_3d/layers/conv2d_same.py
timm_3d/layers/conv_bn_act.py
timm_3d/layers/create_act.py
timm_3d/layers/create_attn.py
timm_3d/layers/create_conv2d.py
timm_3d/layers/create_norm.py
timm_3d/layers/create_norm_act.py
timm_3d/layers/drop.py
timm_3d/layers/eca.py
timm_3d/layers/evo_norm.py
timm_3d/layers/fast_norm.py
timm_3d/layers/filter_response_norm.py
timm_3d/layers/format.py
timm_3d/layers/gather_excite.py
timm_3d/layers/global_context.py
timm_3d/layers/grid.py
timm_3d/layers/grn.py
timm_3d/layers/halo_attn.py
timm_3d/layers/helpers.py
timm_3d/layers/inplace_abn.py
timm_3d/layers/interpolate.py
timm_3d-1.0.1.dist-info/METADATA
timm_3d-1.0.1.dist-info/WHEEL
timm_3d-1.0.1.dist-info/top_level.txt
timm_3d-1.0.1.dist-info/RECORD
