Metadata-Version: 2.1
Name: timm-3d
Version: 1.0.1
Summary: Python library with Neural Networks for Volume (3D) Classification based on PyTorch.
Home-page: https://github.com/ZFTurbo/timm_3d
Author: Roman Sol (ZFTurbo)
Author-email: UNKNOWN
License: UNKNOWN
Platform: UNKNOWN
Requires-Dist: torch (>=1.7)
Requires-Dist: torchvision
Requires-Dist: pyyaml
Requires-Dist: huggingface-hub
Requires-Dist: safetensors (>=0.2)
